zaku/__init__.py
zaku/base.py
zaku/client.py
zaku/interfaces.py
zaku/job_queue.py
zaku/redis_helpers.py
zaku/server.py
zaku-0.0.18.dist-info/licenses/LICENSE
zaku-0.0.18.dist-info/METADATA
zaku-0.0.18.dist-info/WHEEL
zaku-0.0.18.dist-info/entry_points.txt
zaku-0.0.18.dist-info/top_level.txt
zaku-0.0.18.dist-info/RECORD
