Metadata-Version: 2.4
Name: zaku
Version: 0.0.18
Summary: Zaku Task Queue is for distributed ML-workloads.
Home-page: https://github.com/geyang/zaku
Author: Ge Yang<ge.ike.yang@gmail.com>
Author-email: ge.ike.yang@gmail.com
License: MIT
Classifier: Development Status :: 3 - Alpha
Classifier: Programming Language :: Python
Requires-Python: >=3.7
License-File: LICENSE
Requires-Dist: params-proto>=2.11.16
Requires-Dist: pillow
Requires-Dist: msgpack
Requires-Dist: numpy>=1.21
Requires-Dist: websockets
Provides-Extra: all
Requires-Dist: asyncio; extra == "all"
Requires-Dist: aiohttp; extra == "all"
Requires-Dist: aiohttp-cors; extra == "all"
Requires-Dist: killport; extra == "all"
Requires-Dist: redis; extra == "all"
Provides-Extra: examples
Requires-Dist: aiohttp; extra == "examples"
Requires-Dist: aiohttp-cors; extra == "examples"
Requires-Dist: cmx; extra == "examples"
Requires-Dist: functional_notations; extra == "examples"
Requires-Dist: killport; extra == "examples"
Requires-Dist: ml_logger; extra == "examples"
Requires-Dist: opencv-python; extra == "examples"
Requires-Dist: open3d<0.16.0,>=0.15.0; extra == "examples"
Requires-Dist: redis; extra == "examples"
Requires-Dist: trimesh; extra == "examples"
Provides-Extra: dev
Requires-Dist: restructuredtext-lint; extra == "dev"
Requires-Dist: twine; extra == "dev"
Requires-Dist: aiohttp; extra == "dev"
Requires-Dist: aiohttp-cors; extra == "dev"
Requires-Dist: black==22.3.0; extra == "dev"
Requires-Dist: killport; extra == "dev"
Requires-Dist: redis; extra == "dev"
Requires-Dist: pylint==2.13.4; extra == "dev"
Requires-Dist: pytest==7.1.2; extra == "dev"
Requires-Dist: sphinx==7.1.2; extra == "dev"
Requires-Dist: sphinx-autobuild; extra == "dev"
Requires-Dist: pytest-asyncio; extra == "dev"
Requires-Dist: pytest-dependency; extra == "dev"
Requires-Dist: furo; extra == "dev"
Requires-Dist: sphinx_copybutton; extra == "dev"
Requires-Dist: myst_parser; extra == "dev"
Requires-Dist: trimesh; extra == "dev"
Requires-Dist: tqdm; extra == "dev"
Dynamic: author
Dynamic: author-email
Dynamic: home-page
Dynamic: license-file
